videochef/__init__.py
videochef/chef.py
videochef/io.py
videochef/util.py
videochef/viz.py
videochef-0.2.3.dist-info/licenses/LICENSE.txt
videochef-0.2.3.dist-info/METADATA
videochef-0.2.3.dist-info/WHEEL
videochef-0.2.3.dist-info/top_level.txt
videochef-0.2.3.dist-info/RECORD
