Metadata-Version: 2.4
Name: videochef
Version: 0.2.3
Summary: Whip up some fast, embarrassingly parallel video processing
Home-page: https://github.com/jonahpearl/videochef
Author: Jonah Pearl
Author-email: jonahpearl@g.harvard.edu
License: MIT
Project-URL: Issue Tracker, https://github.com/jonahpearl/videochef/issues
Classifier: Development Status :: 1 - Planning
Classifier: Intended Audience :: Science/Research
Classifier: License :: OSI Approved :: MIT License
Classifier: Operating System :: Unix
Classifier: Operating System :: POSIX
Classifier: Operating System :: Microsoft :: Windows
Classifier: Programming Language :: Python :: 3
Classifier: Topic :: Scientific/Engineering :: Image Processing
Requires-Python: >=3.6
License-File: LICENSE.txt
Requires-Dist: numpy
Requires-Dist: click
Requires-Dist: av
Requires-Dist: tqdm
Dynamic: author
Dynamic: author-email
Dynamic: classifier
Dynamic: home-page
Dynamic: license
Dynamic: license-file
Dynamic: project-url
Dynamic: requires-dist
Dynamic: requires-python
Dynamic: summary
